cpvlib/__init__.py
cpvlib/cpvsystem.py
cpvlib/tests/__init__.py
cpvlib/tests/test_cpvlib.py
cpvlib/tests/test_cpvsystem.py
cpvlib/tests/data/InsolightMay2019.csv
cpvlib/tests/data/StaticHybridSystem block_diagram.png
cpvlib/tests/data/meteo2020_03_04.txt
cpvlib/tests/data/meteo2020_03_14.txt
cpvlib-0.1.5.dist-info/LICENSE
cpvlib-0.1.5.dist-info/METADATA
cpvlib-0.1.5.dist-info/WHEEL
cpvlib-0.1.5.dist-info/top_level.txt
cpvlib-0.1.5.dist-info/RECORD
